{
    "name": "巨人",
    "icon": "xat:titan_ring",
    "category": "races",
    "pages": [
        {
            "type": "text",
            "text": "巨人有难以置信的近战能力但是行动不便。他们也有更大的挖掘范围，3x3x3的范围而不是1x1x1。他们是普通玩家体型的三倍大。因此，他们能轻易践踏耕地并立即在水中沉没。"
        },
		{
            "type": "text",
            "text": "$(l)默认属性调整：$()$(br)300%体型$(br)$(4)-50%$()攻击速度$(br)$(2)+50%$()攻击伤害$(br)$(2)+100%$()生命值$(br)$(2)+30%$()击退抗性$(br)$(4)-25%$()移动速度$(br)$(2)+75%$()跳跃高度$(br)$(2)+1.4$()步行高度"
        },
		{
            "type": "text",
            "text": "$(l)能力：更大挖掘范围$()$(br)巨人能一次挖掘3x3x3的洞，这使他们非常适合挖大洞（尤其是当你想挖掘整个区块）。你可以在挖掘时潜行以禁用这一能力。"
        },
		{
            "type": "crafting",
			"recipe": "xat:titans_spirit",
			"recipe2": "xat:titan_ring"
        }
    ]
}